rstmat/__init__.py
rstmat/matrix.py
rstmat/rng.py
rstmat-0.1.76.dist-info/METADATA
rstmat-0.1.76.dist-info/WHEEL
rstmat-0.1.76.dist-info/top_level.txt
rstmat-0.1.76.dist-info/RECORD
