Metadata-Version: 2.4
Name: rstmat
Version: 0.1.76
Summary: Random structured matrices.
Author-email: Ivan Nikishev <nkshv2@gmail.com>
Project-URL: Homepage, https://github.com/inikishev/rstmat
Project-URL: Repository, https://github.com/inikishev/rstmat
Project-URL: Issues, https://github.com/inikishev/rstmat/isses
Keywords: linear algebra,random,linalg,torch
Requires-Python: >=3.10
Requires-Dist: torch
Requires-Dist: numpy
Requires-Dist: scipy
